plasm/__init__.py
plasm/plasm.py
PLASM-1.0.dev2.dist-info/LICENSE
PLASM-1.0.dev2.dist-info/METADATA
PLASM-1.0.dev2.dist-info/WHEEL
PLASM-1.0.dev2.dist-info/top_level.txt
PLASM-1.0.dev2.dist-info/RECORD
