Metadata-Version: 2.1
Name: PLASM
Version: 1.0.dev2
Summary: PLot Analysis Spreads for Meetings
Home-page: https://github.com/bagrow/plasm
Author: Jim Bagrow
Author-email: bagrowjp@gmail.com
License: UNKNOWN
Platform: UNKNOWN
Classifier: Programming Language :: Python :: 3
Classifier: License :: OSI Approved :: BSD License
Classifier: Operating System :: OS Independent
Requires-Python: >=3.6
Requires-Dist: matplotlib
Requires-Dist: numpy
Requires-Dist: scipy
